lkj/fun.py
lkj_ru-1.0.0.dist-info/LICENSE.txt
lkj_ru-1.0.0.dist-info/METADATA
lkj_ru-1.0.0.dist-info/WHEEL
lkj_ru-1.0.0.dist-info/entry_points.txt
lkj_ru-1.0.0.dist-info/top_level.txt
lkj_ru-1.0.0.dist-info/RECORD
