Metadata-Version: 2.1
Name: lkj-ru
Version: 1.0.0
Summary: A Python package to get random number between 10 to 20
Home-page: https://github.com/tirth-2001/lkj-ru.git
Author: Tirth Patel
Author-email: tirthgpatel.27@gmail.com
License: MIT
Platform: UNKNOWN
Classifier: License :: OSI Approved :: MIT License
Classifier: Programming Language :: Python :: 3
Classifier: Programming Language :: Python :: 3.7
Requires-Dist: random
